drumbo/.song.py.swp
drumbo/__init__.py
drumbo/__main__.py
drumbo/cli.py
drumbo/song.py
drumbo/drums/.__init__.py.swp
drumbo/drums/.hihat.py.swp
drumbo/drums/.instrument.py.swp
drumbo/drums/.kick.py.swp
drumbo/drums/.snare.py.swp
drumbo/drums/__init__.py
drumbo/drums/hihat.py
drumbo/drums/instrument.py
drumbo/drums/kick.py
drumbo/drums/snare.py
drumbo-0.2.0.dist-info/DESCRIPTION.rst
drumbo-0.2.0.dist-info/METADATA
drumbo-0.2.0.dist-info/RECORD
drumbo-0.2.0.dist-info/WHEEL
drumbo-0.2.0.dist-info/entry_points.txt
drumbo-0.2.0.dist-info/metadata.json
drumbo-0.2.0.dist-info/top_level.txt
